{"_path":"/navigation-aria","_dir":"","_draft":false,"_partial":false,"_locale":"","title":"Navigation Aria","description":"","body":{"type":"root","children":[{"type":"element","tag":"pre","props":{"className":"language-html shiki shiki-themes dark-plus","code":"<nav role=\"navigation\">\n  <ul role=\"menubar\">\n    <li role=\"menuitem\"><a href=\"#\">Link 1</a></li>\n    <li role=\"menuitem\"><a href=\"#\">Link 2</a></li>\n    <li role=\"menuitem\" aria-haspopup=\"true\">\n      <a href=\"#\">Link 3</a>\n      <ul role=\"menu\" aria-hidden=\"true\">\n        <li role=\"menuitem\"><a href=\"#\">Sub Link 1</a></li>\n        <li role=\"menuitem\"><a href=\"#\">Sub Link 2</a></li>\n      </ul>\n    </li>\n  </ul>\n</nav>\n","language":"html","meta":"","style":""},"children":[{"type":"element","tag":"code","props":{"__ignoreMap":""},"children":[{"type":"element","tag":"span","props":{"class":"line","line":1},"children":[{"type":"element","tag":"span","props":{"style":"--shiki-default:#808080"},"children":[{"type":"text","value":"<"}]},{"type":"element","tag":"span","props":{"style":"--shiki-default:#569CD6"},"children":[{"type":"text","value":"nav"}]},{"type":"element","tag":"span","props":{"style":"--shiki-default:#9CDCFE"},"children":[{"type":"text","value":" role"}]},{"type":"element","tag":"span","props":{"style":"--shiki-default:#D4D4D4"},"children":[{"type":"text","value":"="}]},{"type":"element","tag":"span","props":{"style":"--shiki-default:#CE9178"},"children":[{"type":"text","value":"\"navigation\""}]},{"type":"element","tag":"span","props":{"style":"--shiki-default:#808080"},"children":[{"type":"text","value":">\n"}]}]},{"type":"element","tag":"span","props":{"class":"line","line":2},"children":[{"type":"element","tag":"span","props":{"style":"--shiki-default:#808080"},"children":[{"type":"text","value":"  <"}]},{"type":"element","tag":"span","props":{"style":"--shiki-default:#569CD6"},"children":[{"type":"text","value":"ul"}]},{"type":"element","tag":"span","props":{"style":"--shiki-default:#9CDCFE"},"children":[{"type":"text","value":" role"}]},{"type":"element","tag":"span","props":{"style":"--shiki-default:#D4D4D4"},"children":[{"type":"text","value":"="}]},{"type":"element","tag":"span","props":{"style":"--shiki-default:#CE9178"},"children":[{"type":"text","value":"\"menubar\""}]},{"type":"element","tag":"span","props":{"style":"--shiki-default:#808080"},"children":[{"type":"text","value":">\n"}]}]},{"type":"element","tag":"span","props":{"class":"line","line":3},"children":[{"type":"element","tag":"span","props":{"style":"--shiki-default:#808080"},"children":[{"type":"text","value":"    <"}]},{"type":"element","tag":"span","props":{"style":"--shiki-default:#569CD6"},"children":[{"type":"text","value":"li"}]},{"type":"element","tag":"span","props":{"style":"--shiki-default:#9CDCFE"},"children":[{"type":"text","value":" role"}]},{"type":"element","tag":"span","props":{"style":"--shiki-default:#D4D4D4"},"children":[{"type":"text","value":"="}]},{"type":"element","tag":"span","props":{"style":"--shiki-default:#CE9178"},"children":[{"type":"text","value":"\"menuitem\""}]},{"type":"element","tag":"span","props":{"style":"--shiki-default:#808080"},"children":[{"type":"text","value":"><"}]},{"type":"element","tag":"span","props":{"style":"--shiki-default:#569CD6"},"children":[{"type":"text","value":"a"}]},{"type":"element","tag":"span","props":{"style":"--shiki-default:#9CDCFE"},"children":[{"type":"text","value":" href"}]},{"type":"element","tag":"span","props":{"style":"--shiki-default:#D4D4D4"},"children":[{"type":"text","value":"="}]},{"type":"element","tag":"span","props":{"style":"--shiki-default:#CE9178"},"children":[{"type":"text","value":"\"#\""}]},{"type":"element","tag":"span","props":{"style":"--shiki-default:#808080"},"children":[{"type":"text","value":">"}]},{"type":"element","tag":"span","props":{"style":"--shiki-default:#D4D4D4"},"children":[{"type":"text","value":"Link 1"}]},{"type":"element","tag":"span","props":{"style":"--shiki-default:#808080"},"children":[{"type":"text","value":"</"}]},{"type":"element","tag":"span","props":{"style":"--shiki-default:#569CD6"},"children":[{"type":"text","value":"a"}]},{"type":"element","tag":"span","props":{"style":"--shiki-default:#808080"},"children":[{"type":"text","value":"></"}]},{"type":"element","tag":"span","props":{"style":"--shiki-default:#569CD6"},"children":[{"type":"text","value":"li"}]},{"type":"element","tag":"span","props":{"style":"--shiki-default:#808080"},"children":[{"type":"text","value":">\n"}]}]},{"type":"element","tag":"span","props":{"class":"line","line":4},"children":[{"type":"element","tag":"span","props":{"style":"--shiki-default:#808080"},"children":[{"type":"text","value":"    <"}]},{"type":"element","tag":"span","props":{"style":"--shiki-default:#569CD6"},"children":[{"type":"text","value":"li"}]},{"type":"element","tag":"span","props":{"style":"--shiki-default:#9CDCFE"},"children":[{"type":"text","value":" role"}]},{"type":"element","tag":"span","props":{"style":"--shiki-default:#D4D4D4"},"children":[{"type":"text","value":"="}]},{"type":"element","tag":"span","props":{"style":"--shiki-default:#CE9178"},"children":[{"type":"text","value":"\"menuitem\""}]},{"type":"element","tag":"span","props":{"style":"--shiki-default:#808080"},"children":[{"type":"text","value":"><"}]},{"type":"element","tag":"span","props":{"style":"--shiki-default:#569CD6"},"children":[{"type":"text","value":"a"}]},{"type":"element","tag":"span","props":{"style":"--shiki-default:#9CDCFE"},"children":[{"type":"text","value":" href"}]},{"type":"element","tag":"span","props":{"style":"--shiki-default:#D4D4D4"},"children":[{"type":"text","value":"="}]},{"type":"element","tag":"span","props":{"style":"--shiki-default:#CE9178"},"children":[{"type":"text","value":"\"#\""}]},{"type":"element","tag":"span","props":{"style":"--shiki-default:#808080"},"children":[{"type":"text","value":">"}]},{"type":"element","tag":"span","props":{"style":"--shiki-default:#D4D4D4"},"children":[{"type":"text","value":"Link 2"}]},{"type":"element","tag":"span","props":{"style":"--shiki-default:#808080"},"children":[{"type":"text","value":"</"}]},{"type":"element","tag":"span","props":{"style":"--shiki-default:#569CD6"},"children":[{"type":"text","value":"a"}]},{"type":"element","tag":"span","props":{"style":"--shiki-default:#808080"},"children":[{"type":"text","value":"></"}]},{"type":"element","tag":"span","props":{"style":"--shiki-default:#569CD6"},"children":[{"type":"text","value":"li"}]},{"type":"element","tag":"span","props":{"style":"--shiki-default:#808080"},"children":[{"type":"text","value":">\n"}]}]},{"type":"element","tag":"span","props":{"class":"line","line":5},"children":[{"type":"element","tag":"span","props":{"style":"--shiki-default:#808080"},"children":[{"type":"text","value":"    <"}]},{"type":"element","tag":"span","props":{"style":"--shiki-default:#569CD6"},"children":[{"type":"text","value":"li"}]},{"type":"element","tag":"span","props":{"style":"--shiki-default:#9CDCFE"},"children":[{"type":"text","value":" role"}]},{"type":"element","tag":"span","props":{"style":"--shiki-default:#D4D4D4"},"children":[{"type":"text","value":"="}]},{"type":"element","tag":"span","props":{"style":"--shiki-default:#CE9178"},"children":[{"type":"text","value":"\"menuitem\""}]},{"type":"element","tag":"span","props":{"style":"--shiki-default:#9CDCFE"},"children":[{"type":"text","value":" aria-haspopup"}]},{"type":"element","tag":"span","props":{"style":"--shiki-default:#D4D4D4"},"children":[{"type":"text","value":"="}]},{"type":"element","tag":"span","props":{"style":"--shiki-default:#CE9178"},"children":[{"type":"text","value":"\"true\""}]},{"type":"element","tag":"span","props":{"style":"--shiki-default:#808080"},"children":[{"type":"text","value":">\n"}]}]},{"type":"element","tag":"span","props":{"class":"line","line":6},"children":[{"type":"element","tag":"span","props":{"style":"--shiki-default:#808080"},"children":[{"type":"text","value":"      <"}]},{"type":"element","tag":"span","props":{"style":"--shiki-default:#569CD6"},"children":[{"type":"text","value":"a"}]},{"type":"element","tag":"span","props":{"style":"--shiki-default:#9CDCFE"},"children":[{"type":"text","value":" href"}]},{"type":"element","tag":"span","props":{"style":"--shiki-default:#D4D4D4"},"children":[{"type":"text","value":"="}]},{"type":"element","tag":"span","props":{"style":"--shiki-default:#CE9178"},"children":[{"type":"text","value":"\"#\""}]},{"type":"element","tag":"span","props":{"style":"--shiki-default:#808080"},"children":[{"type":"text","value":">"}]},{"type":"element","tag":"span","props":{"style":"--shiki-default:#D4D4D4"},"children":[{"type":"text","value":"Link 3"}]},{"type":"element","tag":"span","props":{"style":"--shiki-default:#808080"},"children":[{"type":"text","value":"</"}]},{"type":"element","tag":"span","props":{"style":"--shiki-default:#569CD6"},"children":[{"type":"text","value":"a"}]},{"type":"element","tag":"span","props":{"style":"--shiki-default:#808080"},"children":[{"type":"text","value":">\n"}]}]},{"type":"element","tag":"span","props":{"class":"line","line":7},"children":[{"type":"element","tag":"span","props":{"style":"--shiki-default:#808080"},"children":[{"type":"text","value":"      <"}]},{"type":"element","tag":"span","props":{"style":"--shiki-default:#569CD6"},"children":[{"type":"text","value":"ul"}]},{"type":"element","tag":"span","props":{"style":"--shiki-default:#9CDCFE"},"children":[{"type":"text","value":" role"}]},{"type":"element","tag":"span","props":{"style":"--shiki-default:#D4D4D4"},"children":[{"type":"text","value":"="}]},{"type":"element","tag":"span","props":{"style":"--shiki-default:#CE9178"},"children":[{"type":"text","value":"\"menu\""}]},{"type":"element","tag":"span","props":{"style":"--shiki-default:#9CDCFE"},"children":[{"type":"text","value":" aria-hidden"}]},{"type":"element","tag":"span","props":{"style":"--shiki-default:#D4D4D4"},"children":[{"type":"text","value":"="}]},{"type":"element","tag":"span","props":{"style":"--shiki-default:#CE9178"},"children":[{"type":"text","value":"\"true\""}]},{"type":"element","tag":"span","props":{"style":"--shiki-default:#808080"},"children":[{"type":"text","value":">\n"}]}]},{"type":"element","tag":"span","props":{"class":"line","line":8},"children":[{"type":"element","tag":"span","props":{"style":"--shiki-default:#808080"},"children":[{"type":"text","value":"        <"}]},{"type":"element","tag":"span","props":{"style":"--shiki-default:#569CD6"},"children":[{"type":"text","value":"li"}]},{"type":"element","tag":"span","props":{"style":"--shiki-default:#9CDCFE"},"children":[{"type":"text","value":" role"}]},{"type":"element","tag":"span","props":{"style":"--shiki-default:#D4D4D4"},"children":[{"type":"text","value":"="}]},{"type":"element","tag":"span","props":{"style":"--shiki-default:#CE9178"},"children":[{"type":"text","value":"\"menuitem\""}]},{"type":"element","tag":"span","props":{"style":"--shiki-default:#808080"},"children":[{"type":"text","value":"><"}]},{"type":"element","tag":"span","props":{"style":"--shiki-default:#569CD6"},"children":[{"type":"text","value":"a"}]},{"type":"element","tag":"span","props":{"style":"--shiki-default:#9CDCFE"},"children":[{"type":"text","value":" href"}]},{"type":"element","tag":"span","props":{"style":"--shiki-default:#D4D4D4"},"children":[{"type":"text","value":"="}]},{"type":"element","tag":"span","props":{"style":"--shiki-default:#CE9178"},"children":[{"type":"text","value":"\"#\""}]},{"type":"element","tag":"span","props":{"style":"--shiki-default:#808080"},"children":[{"type":"text","value":">"}]},{"type":"element","tag":"span","props":{"style":"--shiki-default:#D4D4D4"},"children":[{"type":"text","value":"Sub Link 1"}]},{"type":"element","tag":"span","props":{"style":"--shiki-default:#808080"},"children":[{"type":"text","value":"</"}]},{"type":"element","tag":"span","props":{"style":"--shiki-default:#569CD6"},"children":[{"type":"text","value":"a"}]},{"type":"element","tag":"span","props":{"style":"--shiki-default:#808080"},"children":[{"type":"text","value":"></"}]},{"type":"element","tag":"span","props":{"style":"--shiki-default:#569CD6"},"children":[{"type":"text","value":"li"}]},{"type":"element","tag":"span","props":{"style":"--shiki-default:#808080"},"children":[{"type":"text","value":">\n"}]}]},{"type":"element","tag":"span","props":{"class":"line","line":9},"children":[{"type":"element","tag":"span","props":{"style":"--shiki-default:#808080"},"children":[{"type":"text","value":"        <"}]},{"type":"element","tag":"span","props":{"style":"--shiki-default:#569CD6"},"children":[{"type":"text","value":"li"}]},{"type":"element","tag":"span","props":{"style":"--shiki-default:#9CDCFE"},"children":[{"type":"text","value":" role"}]},{"type":"element","tag":"span","props":{"style":"--shiki-default:#D4D4D4"},"children":[{"type":"text","value":"="}]},{"type":"element","tag":"span","props":{"style":"--shiki-default:#CE9178"},"children":[{"type":"text","value":"\"menuitem\""}]},{"type":"element","tag":"span","props":{"style":"--shiki-default:#808080"},"children":[{"type":"text","value":"><"}]},{"type":"element","tag":"span","props":{"style":"--shiki-default:#569CD6"},"children":[{"type":"text","value":"a"}]},{"type":"element","tag":"span","props":{"style":"--shiki-default:#9CDCFE"},"children":[{"type":"text","value":" href"}]},{"type":"element","tag":"span","props":{"style":"--shiki-default:#D4D4D4"},"children":[{"type":"text","value":"="}]},{"type":"element","tag":"span","props":{"style":"--shiki-default:#CE9178"},"children":[{"type":"text","value":"\"#\""}]},{"type":"element","tag":"span","props":{"style":"--shiki-default:#808080"},"children":[{"type":"text","value":">"}]},{"type":"element","tag":"span","props":{"style":"--shiki-default:#D4D4D4"},"children":[{"type":"text","value":"Sub Link 2"}]},{"type":"element","tag":"span","props":{"style":"--shiki-default:#808080"},"children":[{"type":"text","value":"</"}]},{"type":"element","tag":"span","props":{"style":"--shiki-default:#569CD6"},"children":[{"type":"text","value":"a"}]},{"type":"element","tag":"span","props":{"style":"--shiki-default:#808080"},"children":[{"type":"text","value":"></"}]},{"type":"element","tag":"span","props":{"style":"--shiki-default:#569CD6"},"children":[{"type":"text","value":"li"}]},{"type":"element","tag":"span","props":{"style":"--shiki-default:#808080"},"children":[{"type":"text","value":">\n"}]}]},{"type":"element","tag":"span","props":{"class":"line","line":10},"children":[{"type":"element","tag":"span","props":{"style":"--shiki-default:#808080"},"children":[{"type":"text","value":"      </"}]},{"type":"element","tag":"span","props":{"style":"--shiki-default:#569CD6"},"children":[{"type":"text","value":"ul"}]},{"type":"element","tag":"span","props":{"style":"--shiki-default:#808080"},"children":[{"type":"text","value":">\n"}]}]},{"type":"element","tag":"span","props":{"class":"line","line":11},"children":[{"type":"element","tag":"span","props":{"style":"--shiki-default:#808080"},"children":[{"type":"text","value":"    </"}]},{"type":"element","tag":"span","props":{"style":"--shiki-default:#569CD6"},"children":[{"type":"text","value":"li"}]},{"type":"element","tag":"span","props":{"style":"--shiki-default:#808080"},"children":[{"type":"text","value":">\n"}]}]},{"type":"element","tag":"span","props":{"class":"line","line":12},"children":[{"type":"element","tag":"span","props":{"style":"--shiki-default:#808080"},"children":[{"type":"text","value":"  </"}]},{"type":"element","tag":"span","props":{"style":"--shiki-default:#569CD6"},"children":[{"type":"text","value":"ul"}]},{"type":"element","tag":"span","props":{"style":"--shiki-default:#808080"},"children":[{"type":"text","value":">\n"}]}]},{"type":"element","tag":"span","props":{"class":"line","line":13},"children":[{"type":"element","tag":"span","props":{"style":"--shiki-default:#808080"},"children":[{"type":"text","value":"</"}]},{"type":"element","tag":"span","props":{"style":"--shiki-default:#569CD6"},"children":[{"type":"text","value":"nav"}]},{"type":"element","tag":"span","props":{"style":"--shiki-default:#808080"},"children":[{"type":"text","value":">\n"}]}]}]}]},{"type":"element","tag":"style","props":{},"children":[{"type":"text","value":"html .shiki span {color: var(--shiki-default);background: var(--shiki-default-bg);font-style: var(--shiki-default-font-style);font-weight: var(--shiki-default-font-weight);text-decoration: var(--shiki-default-text-decoration);}html .default .shiki span {color: var(--shiki-default);background: var(--shiki-default-bg);font-style: var(--shiki-default-font-style);font-weight: var(--shiki-default-font-weight);text-decoration: var(--shiki-default-text-decoration);}"}]}],"toc":{"title":"","searchDepth":2,"depth":2,"links":[]}},"_type":"markdown","_id":"content:navigation-aria.md","_source":"content","_file":"navigation-aria.md","_extension":"md"}